erroranalysis/__init__.py
erroranalysis/__main__.py
erroranalysis/ea.py
erroranalysis_py-0.6.11.dist-info/LICENSE
erroranalysis_py-0.6.11.dist-info/METADATA
erroranalysis_py-0.6.11.dist-info/WHEEL
erroranalysis_py-0.6.11.dist-info/entry_points.txt
erroranalysis_py-0.6.11.dist-info/top_level.txt
erroranalysis_py-0.6.11.dist-info/RECORD
